Workbook

Sheet はじめに
A1: Excel 演習用ブック（解答例）
A3: Office研修_予習/02_Excel の各章「やってみよう」と「07_演習問題」で使うデータです。
A4: 黄色のセルが入力欄です。解答例では数式が入っています。
A6: シート一覧
A7: 消費税 … 絶対参照の練習（Excel-02）
A8: 九九 … 複合参照の練習（Excel-02）
A9: 成績表 … 基本関数・IF・RANK の練習（Excel-02, 03）
A10: 売上データ … COUNTIF / SUMIF / 並べ替え / フィルター / ピボット（Excel-03, 05）
A11: 集計 … 地域別・担当者別の集計表（Excel-03）
A12: 商品マスタ … VLOOKUP / XLOOKUP の参照先（Excel-03）
A13: 注文表 … VLOOKUP / XLOOKUP の練習（Excel-03）
A14: 月別売上 … グラフの練習（Excel-06）
A15: 課題管理 … 入力規則・条件付き書式の練習（Excel-04）

Sheet 消費税
A1: 消費税率 | B1: 0.1
A3: 商品 | B3: 価格 | C3: 税込価格
A4: りんご | B4: 100 | C4: =B4*(1+$B$1)
A5: みかん | B5: 200 | C5: =B5*(1+$B$1)
A6: ぶどう | B6: 500 | C6: =B6*(1+$B$1)
A7: メロン | B7: 1200 | C7: =B7*(1+$B$1)
A8: いちご | B8: 680 | C8: =B8*(1+$B$1)

Sheet 九九
B1: 1 | C1: 2 | D1: 3 | E1: 4 | F1: 5 | G1: 6 | H1: 7 | I1: 8 | J1: 9
A2: 1 | B2: =$A2*B$1 | C2: =$A2*C$1 | D2: =$A2*D$1 | E2: =$A2*E$1 | F2: =$A2*F$1 | G2: =$A2*G$1 | H2: =$A2*H$1 | I2: =$A2*I$1 | J2: =$A2*J$1
A3: 2 | B3: =$A3*B$1 | C3: =$A3*C$1 | D3: =$A3*D$1 | E3: =$A3*E$1 | F3: =$A3*F$1 | G3: =$A3*G$1 | H3: =$A3*H$1 | I3: =$A3*I$1 | J3: =$A3*J$1
A4: 3 | B4: =$A4*B$1 | C4: =$A4*C$1 | D4: =$A4*D$1 | E4: =$A4*E$1 | F4: =$A4*F$1 | G4: =$A4*G$1 | H4: =$A4*H$1 | I4: =$A4*I$1 | J4: =$A4*J$1
A5: 4 | B5: =$A5*B$1 | C5: =$A5*C$1 | D5: =$A5*D$1 | E5: =$A5*E$1 | F5: =$A5*F$1 | G5: =$A5*G$1 | H5: =$A5*H$1 | I5: =$A5*I$1 | J5: =$A5*J$1
A6: 5 | B6: =$A6*B$1 | C6: =$A6*C$1 | D6: =$A6*D$1 | E6: =$A6*E$1 | F6: =$A6*F$1 | G6: =$A6*G$1 | H6: =$A6*H$1 | I6: =$A6*I$1 | J6: =$A6*J$1
A7: 6 | B7: =$A7*B$1 | C7: =$A7*C$1 | D7: =$A7*D$1 | E7: =$A7*E$1 | F7: =$A7*F$1 | G7: =$A7*G$1 | H7: =$A7*H$1 | I7: =$A7*I$1 | J7: =$A7*J$1
A8: 7 | B8: =$A8*B$1 | C8: =$A8*C$1 | D8: =$A8*D$1 | E8: =$A8*E$1 | F8: =$A8*F$1 | G8: =$A8*G$1 | H8: =$A8*H$1 | I8: =$A8*I$1 | J8: =$A8*J$1
A9: 8 | B9: =$A9*B$1 | C9: =$A9*C$1 | D9: =$A9*D$1 | E9: =$A9*E$1 | F9: =$A9*F$1 | G9: =$A9*G$1 | H9: =$A9*H$1 | I9: =$A9*I$1 | J9: =$A9*J$1
A10: 9 | B10: =$A10*B$1 | C10: =$A10*C$1 | D10: =$A10*D$1 | E10: =$A10*E$1 | F10: =$A10*F$1 | G10: =$A10*G$1 | H10: =$A10*H$1 | I10: =$A10*I$1 | J10: =$A10*J$1

Sheet 成績表
A1: 氏名 | B1: Word | C1: Excel | D1: PowerPoint | E1: 合計 | F1: 平均 | G1: 順位 | H1: 評価 | I1: Excel合否
A2: 青木 | B2: 78 | C2: 85 | D2: 90 | E2: =SUM(B2:D2) | F2: =ROUND(AVERAGE(B2:D2),1) | G2: =_xlfn.RANK.EQ(E2,$E$2:$E$11) | H2: =IF(F2>=80,"A",IF(F2>=60,"B","C")) | I2: =IF(C2>=60,"合格","不合格")
A3: 井上 | B3: 92 | C3: 88 | D3: 75 | E3: =SUM(B3:D3) | F3: =ROUND(AVERAGE(B3:D3),1) | G3: =_xlfn.RANK.EQ(E3,$E$2:$E$11) | H3: =IF(F3>=80,"A",IF(F3>=60,"B","C")) | I3: =IF(C3>=60,"合格","不合格")
A4: 上田 | B4: 65 | C4: 52 | D4: 70 | E4: =SUM(B4:D4) | F4: =ROUND(AVERAGE(B4:D4),1) | G4: =_xlfn.RANK.EQ(E4,$E$2:$E$11) | H4: =IF(F4>=80,"A",IF(F4>=60,"B","C")) | I4: =IF(C4>=60,"合格","不合格")
A5: 江口 | B5: 88 | C5: 95 | D5: 82 | E5: =SUM(B5:D5) | F5: =ROUND(AVERAGE(B5:D5),1) | G5: =_xlfn.RANK.EQ(E5,$E$2:$E$11) | H5: =IF(F5>=80,"A",IF(F5>=60,"B","C")) | I5: =IF(C5>=60,"合格","不合格")
A6: 大野 | B6: 55 | C6: 61 | D6: 48 | E6: =SUM(B6:D6) | F6: =ROUND(AVERAGE(B6:D6),1) | G6: =_xlfn.RANK.EQ(E6,$E$2:$E$11) | H6: =IF(F6>=80,"A",IF(F6>=60,"B","C")) | I6: =IF(C6>=60,"合格","不合格")
A7: 加藤 | B7: 70 | C7: 74 | D7: 79 | E7: =SUM(B7:D7) | F7: =ROUND(AVERAGE(B7:D7),1) | G7: =_xlfn.RANK.EQ(E7,$E$2:$E$11) | H7: =IF(F7>=80,"A",IF(F7>=60,"B","C")) | I7: =IF(C7>=60,"合格","不合格")
A8: 木村 | B8: 81 | C8: 59 | D8: 88 | E8: =SUM(B8:D8) | F8: =ROUND(AVERAGE(B8:D8),1) | G8: =_xlfn.RANK.EQ(E8,$E$2:$E$11) | H8: =IF(F8>=80,"A",IF(F8>=60,"B","C")) | I8: =IF(C8>=60,"合格","不合格")
A9: 工藤 | B9: 95 | C9: 91 | D9: 93 | E9: =SUM(B9:D9) | F9: =ROUND(AVERAGE(B9:D9),1) | G9: =_xlfn.RANK.EQ(E9,$E$2:$E$11) | H9: =IF(F9>=80,"A",IF(F9>=60,"B","C")) | I9: =IF(C9>=60,"合格","不合格")
A10: 小林 | B10: 60 | C10: 77 | D10: 66 | E10: =SUM(B10:D10) | F10: =ROUND(AVERAGE(B10:D10),1) | G10: =_xlfn.RANK.EQ(E10,$E$2:$E$11) | H10: =IF(F10>=80,"A",IF(F10>=60,"B","C")) | I10: =IF(C10>=60,"合格","不合格")
A11: 斉藤 | B11: 73 | C11: 80 | E11: =SUM(B11:D11) | F11: =ROUND(AVERAGE(B11:D11),1) | G11: =_xlfn.RANK.EQ(E11,$E$2:$E$11) | H11: =IF(F11>=80,"A",IF(F11>=60,"B","C")) | I11: =IF(C11>=60,"合格","不合格")
J12: ※斉藤さんは PowerPoint 未受験（空欄）
A13: 最高点 | B13: =MAX(B2:B11) | C13: =MAX(C2:C11) | D13: =MAX(D2:D11)
A14: 最低点 | B14: =MIN(B2:B11) | C14: =MIN(C2:C11) | D14: =MIN(D2:D11)
A15: 平均点 | B15: =ROUND(AVERAGE(B2:B11),1) | C15: =ROUND(AVERAGE(C2:C11),1) | D15: =ROUND(AVERAGE(D2:D11),1)
A16: 受験者数 | B16: =COUNT(B2:B11) | C16: =COUNT(C2:C11) | D16: =COUNT(D2:D11)
A17: 名簿の人数 | B17: =COUNTA(A2:A11)

Sheet 売上データ
A1: 日付 | B1: 担当者 | C1: 地域 | D1: 商品 | E1: 数量 | F1: 金額 | G1: 区分
A2: 46113 | B2: 佐藤 | C2: 東京 | D2: ノートPC | E2: 2 | F2: 300000 | G2: =IF(F2>=100000,"大口","通常")
A3: 46113 | B3: 鈴木 | C3: 大阪 | D3: マウス | E3: 10 | F3: 30000 | G3: =IF(F3>=100000,"大口","通常")
A4: 46114 | B4: 佐藤 | C4: 東京 | D4: モニター | E4: 3 | F4: 105000 | G4: =IF(F4>=100000,"大口","通常")
A5: 46115 | B5: 高橋 | C5: 名古屋 | D5: ノートPC | E5: 1 | F5: 150000 | G5: =IF(F5>=100000,"大口","通常")
A6: 46115 | B6: 鈴木 | C6: 大阪 | D6: キーボード | E6: 5 | F6: 40000 | G6: =IF(F6>=100000,"大口","通常")
A7: 46116 | B7: 佐藤 | C7: 東京 | D7: ノートPC | E7: 1 | F7: 150000 | G7: =IF(F7>=100000,"大口","通常")
A8: 46116 | B8: 佐藤 | C8: 東京 | D8: キーボード | E8: 2 | F8: 16000 | G8: =IF(F8>=100000,"大口","通常")
A9: 46117 | B9: 鈴木 | C9: 大阪 | D9: ノートPC | E9: 3 | F9: 450000 | G9: =IF(F9>=100000,"大口","通常")
A10: 46118 | B10: 田中 | C10: 東京 | D10: ヘッドセット | E10: 3 | F10: 36000 | G10: =IF(F10>=100000,"大口","通常")
A11: 46120 | B11: 高橋 | C11: 大阪 | D11: ヘッドセット | E11: 7 | F11: 84000 | G11: =IF(F11>=100000,"大口","通常")
A12: 46121 | B12: 佐藤 | C12: 東京 | D12: ノートPC | E12: 1 | F12: 150000 | G12: =IF(F12>=100000,"大口","通常")
A13: 46121 | B13: 田中 | C13: 大阪 | D13: ヘッドセット | E13: 8 | F13: 96000 | G13: =IF(F13>=100000,"大口","通常")
... A61: 46167 | B61: 佐藤 | C61: 名古屋 | D61: キーボード | E61: 3 | F61: 24000 | G61: =IF(F61>=100000,"大口","通常")

Sheet 集計
A1: 地域別集計 | F1: 担当者別集計
A2: 地域 | B2: 件数 | C2: 金額合計 | D2: 平均金額 | F2: 担当者 | G2: 件数 | H2: 金額合計 | I2: 構成比
A3: 東京 | B3: =COUNTIF(売上データ!$C$2:$C$61,A3) | C3: =SUMIF(売上データ!$C$2:$C$61,A3,売上データ!$F$2:$F$61) | D3: =ROUND(AVERAGEIF(売上データ!$C$2:$C$61,A3,売上データ!$F$2:$F$61),0) | F3: 佐藤 | G3: =COUNTIF(売上データ!$B$2:$B$61,F3) | H3: =SUMIF(売上データ!$B$2:$B$61,F3,売上データ!$F$2:$F$61) | I3: =H3/SUM($H$3:$H$6)
A4: 大阪 | B4: =COUNTIF(売上データ!$C$2:$C$61,A4) | C4: =SUMIF(売上データ!$C$2:$C$61,A4,売上データ!$F$2:$F$61) | D4: =ROUND(AVERAGEIF(売上データ!$C$2:$C$61,A4,売上データ!$F$2:$F$61),0) | F4: 鈴木 | G4: =COUNTIF(売上データ!$B$2:$B$61,F4) | H4: =SUMIF(売上データ!$B$2:$B$61,F4,売上データ!$F$2:$F$61) | I4: =H4/SUM($H$3:$H$6)
A5: 名古屋 | B5: =COUNTIF(売上データ!$C$2:$C$61,A5) | C5: =SUMIF(売上データ!$C$2:$C$61,A5,売上データ!$F$2:$F$61) | D5: =ROUND(AVERAGEIF(売上データ!$C$2:$C$61,A5,売上データ!$F$2:$F$61),0) | F5: 高橋 | G5: =COUNTIF(売上データ!$B$2:$B$61,F5) | H5: =SUMIF(売上データ!$B$2:$B$61,F5,売上データ!$F$2:$F$61) | I5: =H5/SUM($H$3:$H$6)
A6: 合計 | B6: =SUM(B3:B5) | C6: =SUM(C3:C5) | F6: 田中 | G6: =COUNTIF(売上データ!$B$2:$B$61,F6) | H6: =SUMIF(売上データ!$B$2:$B$61,F6,売上データ!$F$2:$F$61) | I6: =H6/SUM($H$3:$H$6)
A9: 条件付き集計
A10: 佐藤 かつ 東京 の金額合計 | C10: =SUMIFS(売上データ!$F$2:$F$61,売上データ!$B$2:$B$61,"佐藤",売上データ!$C$2:$C$61,"東京")
A11: ノートPC の販売件数 | C11: =COUNTIF(売上データ!$D$2:$D$61,"ノートPC")
A12: 金額 10 万円以上の件数 | C12: =COUNTIF(売上データ!$F$2:$F$61,">=100000")
A13: 東京以外の金額合計 | C13: =SUMIF(売上データ!$C$2:$C$61,"<>東京",売上データ!$F$2:$F$61)
A14: 5 月の金額合計 | C14: =SUMIFS(売上データ!$F$2:$F$61,売上データ!$A$2:$A$61,">="&DATE(2026,5,1),売上データ!$A$2:$A$61,"<"&DATE(2026,6,1))

Sheet 商品マスタ
A1: コード | B1: 商品名 | C1: 単価
A2: P001 | B2: ノートPC | C2: 150000
A3: P002 | B3: マウス | C3: 3000
A4: P003 | B4: モニター | C4: 35000
A5: P004 | B5: キーボード | C5: 8000
A6: P005 | B6: ヘッドセット | C6: 12000

Sheet 注文表
A1: コード | B1: 商品名 | C1: 単価 | D1: 数量 | E1: 金額
A2: P003 | B2: =IFERROR(VLOOKUP(A2,商品マスタ!$A$2:$C$6,2,FALSE),"コード未登録") | C2: =IFERROR(VLOOKUP(A2,商品マスタ!$A$2:$C$6,3,FALSE),0) | D2: 2 | E2: =C2*D2
A3: P001 | B3: =IFERROR(VLOOKUP(A3,商品マスタ!$A$2:$C$6,2,FALSE),"コード未登録") | C3: =IFERROR(VLOOKUP(A3,商品マスタ!$A$2:$C$6,3,FALSE),0) | D3: 1 | E3: =C3*D3
A4: P005 | B4: =IFERROR(VLOOKUP(A4,商品マスタ!$A$2:$C$6,2,FALSE),"コード未登録") | C4: =IFERROR(VLOOKUP(A4,商品マスタ!$A$2:$C$6,3,FALSE),0) | D4: 4 | E4: =C4*D4
A5: P002 | B5: =IFERROR(VLOOKUP(A5,商品マスタ!$A$2:$C$6,2,FALSE),"コード未登録") | C5: =IFERROR(VLOOKUP(A5,商品マスタ!$A$2:$C$6,3,FALSE),0) | D5: 10 | E5: =C5*D5
A6: P999 | B6: =IFERROR(VLOOKUP(A6,商品マスタ!$A$2:$C$6,2,FALSE),"コード未登録") | C6: =IFERROR(VLOOKUP(A6,商品マスタ!$A$2:$C$6,3,FALSE),0) | D6: 1 | E6: =C6*D6
D7: 合計 | E7: =SUM(E2:E6)

Sheet 月別売上
A1: 支店別 月次売上（千円）
A2: 支店 | B2: 4月 | C2: 5月 | D2: 6月 | E2: 7月 | F2: 8月 | G2: 9月 | H2: 合計
A3: 東京 | B3: 1200 | C3: 1350 | D3: 1280 | E3: 1500 | F3: 1620 | G3: 1580 | H3: =SUM(B3:G3)
A4: 大阪 | B4: 900 | C4: 850 | D4: 880 | E4: 800 | F4: 750 | G4: 820 | H4: =SUM(B4:G4)
A5: 名古屋 | B5: 500 | C5: 540 | D5: 610 | E5: 590 | F5: 650 | G5: 700 | H5: =SUM(B5:G5)
A6: 福岡 | B6: 300 | C6: 320 | D6: 310 | E6: 360 | F6: 380 | G6: 420 | H6: =SUM(B6:G6)
A7: 合計 | B7: =SUM(B3:B6) | C7: =SUM(C3:C6) | D7: =SUM(D3:D6) | E7: =SUM(E3:E6) | F7: =SUM(F3:F6) | G7: =SUM(G3:G6) | H7: =SUM(H3:H6)
A8: 前月比 | C8: =C7/B7 | D8: =D7/C7 | E8: =E7/D7 | F8: =F7/E7 | G8: =G7/F7

Sheet 課題管理
A1: No. | B1: 課題 | C1: 担当 | D1: 期限 | E1: ステータス
A2: 1 | B2: ログイン画面の設計 | C2: 佐藤 | D2: 46309 | E2: 完了
A3: 2 | B3: DB テーブル定義の作成 | C3: 鈴木 | D3: 46311 | E3: 対応中
A4: 3 | B4: テスト仕様書の作成 | C4: 高橋 | D4: 46315 | E4: 未着手
A5: 4 | B5: 画面遷移図のレビュー | C5: 田中 | D5: 46308 | E5: 完了
A6: 5 | B6: API 一覧の作成 | C6: 佐藤 | D6: 46316 | E6: 対応中
A7: 6 | B7: 議事録の共有 | C7: 松尾 | D7: 46307 | E7: 未着手
